odoo/addons/currency_rate_update_hr_hnb/README.rst
odoo/addons/currency_rate_update_hr_hnb/__init__.py
odoo/addons/currency_rate_update_hr_hnb/__manifest__.py
odoo/addons/currency_rate_update_hr_hnb/data/provider_parameter.xml
odoo/addons/currency_rate_update_hr_hnb/i18n/currency_rate_update_hr_hnb.pot
odoo/addons/currency_rate_update_hr_hnb/models/__init__.py
odoo/addons/currency_rate_update_hr_hnb/models/res_currency_rate_provider_HR_HNB.py
odoo/addons/currency_rate_update_hr_hnb/readme/CONFIGURE.rst
odoo/addons/currency_rate_update_hr_hnb/readme/CONTRIBUTORS.rst
odoo/addons/currency_rate_update_hr_hnb/readme/DESCRIPTION.rst
odoo/addons/currency_rate_update_hr_hnb/static/description/icon.png
odoo/addons/currency_rate_update_hr_hnb/static/description/index.html
odoo_addon_currency_rate_update_hr_hnb-16.0.1.0.0.4.dist-info/METADATA
odoo_addon_currency_rate_update_hr_hnb-16.0.1.0.0.4.dist-info/WHEEL
odoo_addon_currency_rate_update_hr_hnb-16.0.1.0.0.4.dist-info/top_level.txt
odoo_addon_currency_rate_update_hr_hnb-16.0.1.0.0.4.dist-info/RECORD
